krakencli/__init__.py
krakencli/kraken_api.py
krakencli/exceptions/__init__.py
krakencli/exceptions/kraken_api_exception.py
krakencli/models/__init__.py
krakenstream/__init__.py
krakenstream/kraken_api.py
krakenstream/exceptions/__init__.py
krakenstream/exceptions/kraken_api_exception.py
krakenstream/models/__init__.py
krakenstream-0.1.0.dist-info/LICENSE
krakenstream-0.1.0.dist-info/METADATA
krakenstream-0.1.0.dist-info/WHEEL
krakenstream-0.1.0.dist-info/top_level.txt
krakenstream-0.1.0.dist-info/RECORD
