Metadata-Version: 2.1
Name: krakenstream
Version: 0.1.0
Summary: A simple Python client to interact with the Kraken cryptocurrency exchange API.
Home-page: https://github.com/gahfy/krakenstream
Author: gahfy
Author-email: g.herfray@gahfy.io
License: UNKNOWN
Platform: UNKNOWN
Classifier: Programming Language :: Python :: 3
Classifier: License :: OSI Approved :: MIT License
Classifier: Operating System :: OS Independent
Requires-Python: >=3.5
License-File: LICENSE
